serverless_openai/__init__.py
serverless_openai/apis.py
serverless_openai/helpers.py
serverless_openai-1.3.8.dist-info/METADATA
serverless_openai-1.3.8.dist-info/WHEEL
serverless_openai-1.3.8.dist-info/top_level.txt
serverless_openai-1.3.8.dist-info/RECORD
