Metadata-Version: 2.1
Name: serverless_openai
Version: 1.3.8
Summary: A package for using Openai in serverless environment
Author: Jayr Castro
Author-email: jayrcastro.py@gmail.com
Keywords: serverless,openai,aws lambda,cloud functions,openai API
Classifier: Development Status :: 4 - Beta
Classifier: Intended Audience :: Developers
Classifier: Programming Language :: Python :: 3.10
Classifier: Operating System :: Unix
Classifier: Operating System :: MacOS :: MacOS X
Classifier: Operating System :: Microsoft :: Windows
Requires-Dist: pydantic ==2.5.3
Requires-Dist: beautifulsoup4 ==4.12.2
Requires-Dist: opencv-python-headless ==4.9.0.80
Requires-Dist: requests ==2.28.2
Requires-Dist: typing-extensions ==4.9.0
Requires-Dist: tiktoken ==0.5.2
